sql_upsert/__init__.py
sql_upsert/upsert.py
sql_upsert-0.1.2.dist-info/METADATA
sql_upsert-0.1.2.dist-info/WHEEL
sql_upsert-0.1.2.dist-info/top_level.txt
sql_upsert-0.1.2.dist-info/RECORD
