Metadata-Version: 2.1
Name: sql_upsert
Version: 0.1.2
Summary: A package for handling SQL upsert operations with pandas DataFrames
Home-page: https://github.com/vile319/sql_upsert
Author: vile319
Author-email: vile319@gmail.com
Classifier: Programming Language :: Python :: 3
Classifier: License :: OSI Approved :: MIT License
Classifier: Operating System :: OS Independent
Requires-Python: >=3.6
Requires-Dist: sqlalchemy>=1.4.0
Requires-Dist: pandas>=1.0.0
